kepi/__init__.py
kepi/bowler_pub/__init__.py
kepi/bowler_pub/activityresponse.py
kepi/bowler_pub/admin.py
kepi/bowler_pub/create.py
kepi/bowler_pub/crypto.py
kepi/bowler_pub/parsers.py
kepi/bowler_pub/renderers.py
kepi/bowler_pub/serializers.py
kepi/bowler_pub/signals.py
kepi/bowler_pub/urls.py
kepi/bowler_pub/utils.py
kepi/bowler_pub/validation.py
kepi/bowler_pub/migrations/0001_initial.py
kepi/bowler_pub/migrations/0002_delete_fetch.py
kepi/bowler_pub/migrations/0003_incomingmessage.py
kepi/bowler_pub/migrations/0004_remove_incomingmessage_is_local_user.py
kepi/bowler_pub/migrations/__init__.py
kepi/bowler_pub/models/__init__.py
kepi/bowler_pub/models/incoming.py
kepi/bowler_pub/static/defaults/avatar_0.jpg
kepi/bowler_pub/static/defaults/avatar_1.jpg
kepi/bowler_pub/static/defaults/avatar_2.jpg
kepi/bowler_pub/static/defaults/avatar_3.jpg
kepi/bowler_pub/static/defaults/avatar_4.jpg
kepi/bowler_pub/static/defaults/avatar_5.jpg
kepi/bowler_pub/static/defaults/avatar_6.jpg
kepi/bowler_pub/static/defaults/avatar_7.jpg
kepi/bowler_pub/static/defaults/avatar_8.jpg
kepi/bowler_pub/static/defaults/avatar_9.jpg
kepi/bowler_pub/static/defaults/avatar_fullsize.jpg
kepi/bowler_pub/static/defaults/header.jpg
kepi/bowler_pub/static/testing/alice.jpg
kepi/bowler_pub/static/testing/bob.jpg
kepi/bowler_pub/static/testing/carol.jpg
kepi/bowler_pub/tests/__init__.py
kepi/bowler_pub/tests/test_collections.py
kepi/bowler_pub/tests/test_delete.py
kepi/bowler_pub/tests/test_headers.py
kepi/bowler_pub/tests/test_send_to_inbox.py
kepi/bowler_pub/tests/test_update.py
kepi/bowler_pub/tests/test_validation.py
kepi/bowler_pub/tests/test_views.py
kepi/bowler_pub/tests/verify-examples.py
kepi/bowler_pub/tests/keys/instances.pem
kepi/bowler_pub/tests/keys/keys-0000.json
kepi/bowler_pub/tests/keys/keys-0001.json
kepi/bowler_pub/tests/keys/keys-0002.json
kepi/bowler_pub/tests/keys/keys-0003.json
kepi/bowler_pub/tests/keys/marnanel.pem
kepi/bowler_pub/tests/mastodon/README.md
kepi-0.7.dist-info/LICENSE.txt
kepi-0.7.dist-info/METADATA
kepi-0.7.dist-info/WHEEL
kepi-0.7.dist-info/top_level.txt
kepi-0.7.dist-info/RECORD
