Metadata-Version: 2.1
Name: kepi
Version: 0.7
Summary: ActivityPub and Mastodon-alike social media
Home-page: https://kepi.org.uk
Author: Marnanel Thurman
Author-email: marnanel@thurman.org.uk
License: GPL-2
Platform: UNKNOWN
Classifier: Environment :: No Input/Output (Daemon)
Classifier: Framework :: Django
Classifier: Topic :: Communications :: Conferencing
Requires-Python: >=3.0
